xsltemplates
