Metadata-Version: 1.0
Name: XSLTemplates
Version: 0.6
Summary: An XSLT based template system for WSGI applications.
Home-page: UNKNOWN
Author: Eric Larson
Author-email: eric@ionrock.org
License: BSD
Keywords: xml xslt wsgi template
Platform: UNKNOWN
Classifier: Environment :: Web Environment
Classifier: License :: OSI Approved :: BSD License
Classifier: Operating System :: OS Independent
Classifier: Programming Language :: Python
Classifier: Topic :: Internet :: WWW/HTTP :: Dynamic Content
Classifier: Topic :: Software Development :: Libraries :: Python Modules
Classifier: Topic :: Text Processing :: Markup :: HTML
Classifier: Topic :: Text Processing :: Markup :: XML
Classifier: Topic :: Internet :: WWW/HTTP :: WSGI :: Middleware
